dbsamizdat/__init__.py
dbsamizdat/api.py
dbsamizdat/apps.py
dbsamizdat/const.py
dbsamizdat/django_api.py
dbsamizdat/exceptions.py
dbsamizdat/graphvizdot.py
dbsamizdat/libdb.py
dbsamizdat/libgraph.py
dbsamizdat/loader.py
dbsamizdat/models.py
dbsamizdat/runner.py
dbsamizdat/samizdat.py
dbsamizdat/util.py
dbsamizdat/management/commands/dbsamizdat.py
dbsamizdat-0.11.1.dist-info/licenses/LICENSE.txt
dbsamizdat-0.11.1.dist-info/METADATA
dbsamizdat-0.11.1.dist-info/WHEEL
dbsamizdat-0.11.1.dist-info/entry_points.txt
dbsamizdat-0.11.1.dist-info/top_level.txt
dbsamizdat-0.11.1.dist-info/zip-safe
dbsamizdat-0.11.1.dist-info/RECORD
