Metadata-Version: 2.4
Name: DBSamizdat
Version: 0.11.1
Summary: dbsamizdat — the blissfully naive PostgreSQL database object manager
Home-page: https://sr.ht/~nullenenenen/DBSamizdat/
Author: nullenenenen
Author-email: nullenenenen@gavagai.eu
License: MPL-2.0
Project-URL: Documentation, https://git.sr.ht/~nullenenenen/DBSamizdat/tree/master/item/README.md
Project-URL: Source, https://git.sr.ht/~nullenenenen/DBSamizdat/
Keywords: PostgreSQL Django
Classifier: Development Status :: 5 - Production/Stable
Classifier: Environment :: Console
Classifier: Intended Audience :: Developers
Classifier: Operating System :: OS Independent
Classifier: Topic :: Software Development
Classifier: Topic :: Database
Classifier: Programming Language :: Python :: 3
Requires-Python: >=3.11
License-File: LICENSE.txt
Requires-Dist: toposort>=1.5
Requires-Dist: psycopg>=3.2.0
Dynamic: license-file
